csv_splitter/__init__.py
csv_splitter/csv_filter_spliter.py
csv_splitter/csv_splitter.tcss
csv_splitter/csv_splitter_interface.py
csv_splitter/pd_datatable.py
csv_filter_splitter-0.1.0.dist-info/METADATA
csv_filter_splitter-0.1.0.dist-info/WHEEL
csv_filter_splitter-0.1.0.dist-info/entry_points.txt
csv_filter_splitter-0.1.0.dist-info/top_level.txt
csv_filter_splitter-0.1.0.dist-info/RECORD
